gitlexpy/__init__.py
gitlexpy/main.py
GitLexPy-0.1.0.dist-info/LICENSE.md
GitLexPy-0.1.0.dist-info/METADATA
GitLexPy-0.1.0.dist-info/WHEEL
GitLexPy-0.1.0.dist-info/entry_points.txt
GitLexPy-0.1.0.dist-info/top_level.txt
GitLexPy-0.1.0.dist-info/RECORD
