Metadata-Version: 2.1
Name: GitLexPy
Version: 0.1.0
Summary: A Python package for generating commit messages using OpenAI
Home-page: https://github.com/krjordan/GitLexPy
Author: Ryan Jordan
Author-email: ryan@ryanjordan.me
Classifier: Programming Language :: Python :: 3
Classifier: License :: OSI Approved :: MIT License
Classifier: Operating System :: OS Independent
Requires-Python: >=3.6
License-File: LICENSE.md
Requires-Dist: gitpython
Requires-Dist: openai
Requires-Dist: argparse
